lab4/half_adder.v
// Lab 4
// Created by David Tran
// Last Modified 02-06-2014

module half_adder(x, y, s, c);

  input x, y;

  output s, c;
  wire s, c;

  assign s=x^y;
  assign c=x&y;

endmodule

lab4/full_adder.v
// Lab 4
// Created by David Tran
// Last Modified 02-05-2014
`include "half_adder.v"

module full_adder(x, y, z, s, c);

  input x, y, z;
  wire x, y, 1;

  output s, c;
  wire s, c;

  wire ws, wc1, wc2;

  half_adder M1 (x, y, ws, wc1);
  half_adder M2 (ws, z, s, wc2);

  assign c=wc1|wc2;

endmodule

labs/lab4/four_bit_adder.v
// Lab 4
// Created by David Tran
// Last Modified 02-05-2014

`include "full_adder.v"

module four_bit_adder(a0, a1, a2, a3, b0, b1, b2, b3, c0,
    d0, d1, d2, d3, d4);

  input a0, a1, a2, a3, b0, b1, b2, b3, c0;
  wire a0, a1, a2, a3, b0, b1, b2, b3, c0;

  output d0, d1, d2, d3, d4;
  wire d0, d1, d2, d3, d4;

  wire c1, c2, c3;

  full_adder M1 (a0, b0, c0, d0, c1);
  full_adder M2 (a1, b1, c1, d1, c2);
  full_adder M3 (a2, b2, c2, d2, c3);
  full_adder M4 (a3, b3, c3, d3, d4);

endmodule

lab4/four_bit_adder_tb.v
// Lab 4
// Created by David Tran
// Last Modified 02-05-2014

// extras
`timescale 1 ms /1 us
`include "four_bit_adder.v"

// Testbench Module

module four_bit_adder_tb (A0, A1, A2, A3, B0, B1, B2, B3,

  output A0, A1, A2, A3, B0, B1, B2, B3, C0;
  reg A0, A1, A2, A3, B0, B1, B2, B3, C0;

  wire D0, D1, D2, D3, D4;

  reg t_A0 [5000:0];
  reg t_A1 [5000:0];
  reg t_A2 [5000:0];
  reg t_A3 [5000:0];
  reg t_B0 [5000:0];
  reg t_B1 [5000:0];
  reg t_B2 [5000:0];
  reg t_B3 [5000:0];
  reg t_C0 [5000:0];

  reg t_clock;
  reg [31:0] vectornum; //Values from 0 -> 2^31

  integer fp;

  four_bit_adder I1 (A0, A1, A2, A3, B0, B1, B2, B3, C0, D0, D1, D2, D3, D4);

  //initial #1000 $finish;

  initial
  begin
    t_clock=0;
    forever #5 t_clock=~t_clock;
  end

  initial
  begin
    $readmemb("./bit_str_a_0.txt",t_A0);
    $readmemb("./bit_str_a_1.txt",t_A1);
    $readmemb("./bit_str_a_2.txt",t_A2);
    $readmemb("./bit_str_a_3.txt",t_A3);
    $readmemb("./bit_str_b_0.txt",t_B0);
    $readmemb("./bit_str_b_1.txt",t_B1);
    $readmemb("./bit_str_b_2.txt",t_B2);
    $readmemb("./bit_str_b_3.txt",t_B3);
    $readmemb("./bit_str_c_0.txt",t_C0);
    vectornum=0; // Set test vector 0
  end

  always @(posedge t_clock)
  begin
    A0<=t_A0[vectornum];
    A1<=t_A1[vectornum];
    A2<=t_A2[vectornum];
    A3<=t_A3[vectornum];
    B0<=t_B0[vectornum];
    B1<=t_B1[vectornum];
    B2<=t_B2[vectornum];
    B3<=t_B3[vectornum];
    C0<=t_C0[vectornum];
    vectornum<=vectornum+1;
  end

  initial
  begin
    //fp=$fopen("four_bit_adder_tb.out");
    //$fmonitor(fp, "time=%0d", $time,, "A=%b B=%b D=%b S=%b C=%b", A, B, D, S, C);
    $monitor("time=%03d", $time,,
      //"A0=%b, A1=%b, A2=%b, A3=%b, B0=%b, B1=%b, B2=%b, B3=%b, C0=%b | D0=%b, D1=%b, D2=%b, D3=%b, D4=%b",
      //"A=%b%b%b%b B=%b%b%b%b, C0=%b | D0=%b, D1=%b, D2=%b, D3=%b, D4=%b",
      "A=%b%b%b%b B=%b%b%b%b, C=%b | D=%b%b%b%b%b",
      A3, A2, A1, A0,
      B3, B2, B1, B0,
      C0,
      D4, D3, D2, D1, D0,
      );
    $dumpfile("fulladder.vcd");
    $dumpvars;
    #1000
    //$fclose(fp);
    $finish;
  end

endmodule

lab4/fulladder.vcd
$date
	Fri Feb  7 07:58:33 2014
$end
$version
	Icarus Verilog
$end
$timescale
	1us
$end
$scope module four_bit_adder_tb $end
$var wire 1 ! D4 $end
$var wire 1 " D3 $end
$var wire 1 # D2 $end
$var wire 1 $ D1 $end
$var wire 1 % D0 $end
$var reg 1 & A0 $end
$var reg 1 ' A1 $end
$var reg 1 ( A2 $end
$var reg 1 ) A3 $end
$var reg 1 * B0 $end
$var reg 1 + B1 $end
$var reg 1 , B2 $end
$var reg 1 - B3 $end
$var reg 1 . C0 $end
$var reg 1 / t_clock $end
$var reg 32 0 vectornum [31:0] $end
$scope module I1 $end
$var wire 1 & a0 $end
$var wire 1 ' a1 $end
$var wire 1 ( a2 $end
$var wire 1 ) a3 $end
$var wire 1 * b0 $end
$var wire 1 + b1 $end
$var wire 1 , b2 $end
$var wire 1 - b3 $end
$var wire 1 . c0 $end
$var wire 1 ! d4 $end
$var wire 1 " d3 $end
$var wire 1 # d2 $end
$var wire 1 $ d1 $end
$var wire 1 % d0 $end
$var wire 1 1 c3 $end
$var wire 1 2 c2 $end
$var wire 1 3 c1 $end
$scope module M1 $end
$var wire 1 3 c $end
$var wire 1 & x $end
$var wire 1 * y $end
$var wire 1 . z $end
$var wire 1 4 ws $end
$var wire 1 5 wc2 $end
$var wire 1 6 wc1 $end
$var wire 1 % s $end
$scope module M1 $end
$var wire 1 6 c $end
$var wire 1 4 s $end
$var wire 1 & x $end
$var wire 1 * y $end
$upscope $end
$scope module M2 $end
$var wire 1 5 c $end
$var wire 1 % s $end
$var wire 1 4 x $end
$var wire 1 . y $end
$upscope $end
$upscope $end
$scope module M2 $end
$var wire 1 2 c $end
$var wire 1 ' x $end
$var wire 1 + y $end
$var wire 1 3 z $end
$var wire 1 7 ws $end
$var wire 1 8 wc2 $end
$var wire 1 9 wc1 $end
$var wire 1 $ s $end
$scope module M1 $end
$var wire 1 9 c $end
$var wire 1 7 s $end
$var wire 1 ' x $end
$var wire 1 + y $end
$upscope $end
$scope module M2 $end
$var wire 1 8 c $end
$var wire 1 $ s $end
$var wire 1 7 x $end
$var wire 1 3 y $end
$upscope $end
$upscope $end
$scope module M3 $end
$var wire 1 1 c $end
$var wire 1 ( x $end
$var wire 1 , y $end
$var wire 1 2 z $end
$var wire 1 : ws $end
$var wire 1 ; wc2 $end
$var wire 1 < wc1 $end
$var wire 1 # s $end
$scope module M1 $end
$var wire 1 < c $end
$var wire 1 : s $end
$var wire 1 ( x $end
$var wire 1 , y $end
$upscope $end
$scope module M2 $end
$var wire 1 ; c $end
$var wire 1 # s $end
$var wire 1 : x $end
$var wire 1 2 y $end
$upscope $end
$upscope $end
$scope module M4 $end
$var wire 1 ! c $end
$var wire 1 ) x $end
$var wire 1 - y $end
$var wire 1 1 z $end
$var wire 1 = ws $end
$var wire 1 > wc2 $end
$var wire 1 ? wc1 $end
$var wire 1 " s $end
$scope module M1 $end
$var wire 1 ? c $end
$var wire 1 = s $end
$var wire 1 ) x $end
$var wire 1 - y $end
$upscope $end
$scope module M2 $end
$var wire 1 > c $end
$var wire 1 " s $end
$var wire 1 = x $end
$var wire 1 1 y $end
$upscope $end
$upscope $end
$upscope $end
$upscope $end
$enddefinitions $end
#0
$dumpvars
x?
x>
x=
x<
x;
x:
x9
x8
x7
x6
x5
x4
x3
x2
x1
b0 0
0/
x.
x-
x,
x+
x*
x)
x(
x'
x&
x%
x$
x#
x"
x!
$end
#5000
1"
11
0#
1;
12
0>
1!
0$
18
13
1%
05
0=
1?
1:
0<
17
09
04
16
b1 0
1.
1-
1,
0+
1*
1)
0(
1'
1&
1/
#10000
0/
#15000
01
1#
0;
02
1$
08
1"
0>
0!
03
1=
0?
14
06
b10 0
0.
0-
0&
1/
#20000
0/
#25000
11
0#
1;
12
0$
18
1"
1!
0%
13
0=
1?
04
16
b11 0
1-
1&
1/
#30000
0/
#35000
01
1#
0;
02
1$
08
1"
0>
0!
1%
03
1=
0?
14
06
b100 0
0-
0&
1/
#40000
0/
#45000
13
0#
1$
0%
15
0:
07
b101 0
1.
1-
0,
0*
0)
0'
1&
1/
#50000
0/
#55000
b110 0
1/
#60000
0/
#65000
0$
03
0"
1%
05
0=
04
b111 0
0-
0&
1/
#70000
0/
#75000
1!
1>
11
1;
12
18
13
0#
0%
15
0"
0$
1:
14
1=
17
b1000 0
1,
1*
1)
1'
1/
#80000
0/
#85000
1"
0>
05
0=
1?
04
16
b1001 0
0.
1-
0,
1+
1(
0'
1&
1/
#90000
0/
#95000
0"
1>
1!
1#
0;
08
1%
03
1=
0?
0:
1<
07
19
14
06
b1010 0
0-
1,
1'
0&
1/
#100000
0/
#105000
1$
13
0%
15
b1011 0
1.
1-
0*
0)
1&
1/
#110000
0/
#115000
0#
0>
01
02
05
04
16
0=
1?
0<
09
b1100 0
0.
0,
0+
1*
1)
0(
0'
1/
#120000
0/
#125000
1"
0!
15
14
06
1=
0?
b1101 0
1.
0*
0)
1/
#130000
0/
#135000
1#
1!
11
12
05
04
16
0=
1?
1<
19
b1110 0
0.
1,
1+
1*
1)
1(
1'
1/
#140000
0/
#145000
0#
0$
0!
01
02
1%
03
1=
0?
0<
09
14
06
b1111 0
0-
0,
0+
0(
0'
0&
1/
#150000
0/
#155000
1#
0"
1$
1:
04
0=
17
b10000 0
1.
1,
0*
0)
1'
1/
#160000
0/
#165000
1"
11
0#
1;
12
0$
18
1!
13
0%
1?
16
b10001 0
0.
1-
0,
1+
1*
1)
1(
0'
1&
1/
#170000
0/
#175000
0"
1>
1!
15
14
06
1=
0?
b10010 0
1.
1,
0+
0*
0)
0(
1'
1/
#180000
0/
#185000
0!
03
1"
0>
0$
08
1#
0;
1%
05
0=
07
19
0:
1<
04
b10011 0
0-
1+
1(
0&
1/
#190000
0/
#195000
1"
18
12
1!
0#
1;
11
13
17
09
1?
1:
0<
16
b10100 0
1-
0+
1*
1)
0(
1&
1/
#200000
0/
#205000
0"
01
1#
0;
02
1$
08
0!
03
0?
06
b10101 0
0-
0,
1+
0*
0)
1(
0'
0&
1/
#210000
0/
#215000
b10110 0
1/
#220000
0/
#225000
1!
0#
13
0%
07
1?
0:
16
b10111 0
0.
1-
0+
1*
1)
0(
1&
1/
#230000
0/
#235000
1#
0!
03
1%
1:
0?
17
06
b11000 0
1.
0-
1,
0*
0)
1'
0&
1/
#240000
0/
#245000
0#
1"
0$
0:
14
1=
07
b11001 0
0.
0,
1*
1)
0'
1/
#250000
0/
#255000
1!
0"
1>
1#
11
12
1<
19
b11010 0
1,
1+
1(
1'
1/
#260000
0/
#265000
0!
01
0"
0>
1$
02
1:
0<
04
0=
17
09
b11011 0
1.
0,
0*
0)
0'
1/
#270000
0/
#275000
13
1"
1$
0#
0%
15
1=
07
0:
14
b11100 0
1-
0+
0(
1&
1/
#280000
0/
#285000
0$
03
0"
1%
05
0=
04
b11101 0
0-
0&
1/
#290000
0/
#295000
b11110 0
1/
#300000
0/
#305000
1"
14
1=
b11111 0
0.
1*
1)
1/
#310000
0/
#315000
1!
1$
0"
1>
1#
13
11
12
0%
15
1<
19
b100000 0
1.
1-
1,
1+
0*
0)
1(
1'
1&
1/
#320000
0/
#325000
0"
0!
03
0>
1$
08
02
1#
0;
01
1%
05
0=
17
09
1:
0<
04
b100001 0
0-
0+
0(
0&
1/
#330000
0/
#335000
1"
11
0#
1;
12
0$
18
1!
13
0%
1?
16
b100010 0
0.
1-
1*
1)
1&
1/
#340000
0/
#345000
01
1#
0;
02
1$
08
1"
0>
0!
1%
03
1=
0?
14
06
b100011 0
0-
0&
1/
#350000
0/
#355000
0#
0"
0$
0:
04
0=
07
b100100 0
1.
0,
0*
0)
0'
1/
#360000
0/
#365000
1$
1!
1#
13
1>
11
12
0%
15
1=
1<
19
14
b100101 0
1-
1,
1+
1(
1'
1&
1/
#370000
0/
#375000
1!
0"
1>
0$
18
12
0#
1;
11
17
09
1:
0<
b100110 0
0+
0(
1/
#380000
0/
#385000
01
1#
0;
02
1$
08
0!
03
0"
0>
1%
05
0=
04
b100111 0
0-
0,
1+
1(
0'
0&
1/
#390000
0/
#395000
1!
1>
11
0#
1;
12
0$
18
13
0"
0%
15
1=
14
b101000 0
1-
1,
0+
0(
1'
1&
1/
#400000
0/
#405000
1$
08
1"
0>
1#
0;
05
07
19
04
16
0=
1?
0:
1<
b101001 0
0.
1+
1*
1)
1(
1/
#410000
0/
#415000
0"
01
0!
02
03
1%
1:
0<
0?
17
09
06
b101010 0
1.
0-
0,
0*
0)
0'
0&
1/
#420000
0/
#425000
1!
1>
11
0#
1;
12
0$
18
13
0"
0%
15
1=
14
b101011 0
1-
1,
0+
0(
1'
1&
1/
#430000
0/
#435000
0!
1"
0>
01
1#
0;
02
1$
08
03
1%
05
b101100 0
0.
0-
0,
1+
1*
1)
1(
0'
0&
1/
#440000
0/
#445000
1!
0"
1>
11
0#
1;
12
0$
18
13
0%
15
b101101 0
1.
1-
1,
0+
0*
0)
0(
1'
1&
1/
#450000
0/
#455000
1$
08
1"
0>
1#
0;
05
07
19
04
16
0=
1?
0:
1<
b101110 0
0.
1+
1*
1)
1(
1/
#460000
0/
#465000
0"
1>
1!
15
14
06
1=
0?
b101111 0
1.
0*
0)
1/
#470000
0/
#475000
0!
1"
0>
03
1$
08
02
1#
0;
01
1%
05
17
09
1:
0<
b110000 0
0.
0-
0+
1*
1)
0(
0&
1/
#480000
0/
#485000
b110001 0
0,
1+
1(
0'
1/
#490000
0/
#495000
b110010 0
1/
#500000
0/
#505000
11
1"
0$
12
0:
1<
04
0=
07
19
b110011 0
1.
1,
0*
0)
1'
1/
#510000
0/
#515000
1!
0"
1>
0#
1;
18
13
11
0$
12
0%
15
1=
1:
0<
17
09
14
b110100 0
1-
0,
0'
1&
1/
#520000
0/
#525000
0!
02
01
03
0"
0>
0$
08
0#
0;
1%
05
0=
07
0:
04
b110101 0
0-
0+
0(
0&
1/
#530000
0/
#535000
1$
1!
1#
13
1>
11
12
0%
15
1=
1<
19
14
b110110 0
1-
1,
1+
1(
1'
1&
1/
#540000
0/
#545000
0$
03
1%
05
b110111 0
0.
0-
1*
1)
0&
1/
#550000
0/
#555000
1!
18
0"
1>
13
0$
12
0#
1;
11
0%
15
17
09
1:
0<
b111000 0
1.
1-
0+
0*
0)
0(
1&
1/
#560000
0/
#565000
0!
1"
0>
01
1#
0;
02
1$
08
03
1%
05
b111001 0
0.
0-
1*
1)
0&
1/
#570000
0/
#575000
1!
0"
1>
13
1$
12
1#
11
0%
15
07
19
0:
1<
b111010 0
1.
1-
1+
0*
0)
1(
1&
1/
#580000
0/
#585000
0#
0>
01
02
05
04
16
0=
1?
0<
09
b111011 0
0.
0,
0+
1*
1)
0(
0'
1/
#590000
0/
#595000
b111100 0
1/
#600000
0/
#605000
0$
0!
03
1%
0?
06
b111101 0
1.
0-
0*
0)
0&
1/
#610000
0/
#615000
1"
1#
1$
1!
11
12
13
0%
1?
1<
19
16
b111110 0
0.
1-
1,
1+
1*
1)
1(
1'
1&
1/
#620000
0/
#625000
1"
0$
18
12
0#
1;
11
17
09
1:
0<
b111111 0
0+
0(
1/
#630000
0/
#635000
0"
1>
1!
15
14
06
1=
0?
b1000000 0
1.
0*
0)
1/
#640000
0/
#645000
1"
0>
05
04
16
0=
1?
b1000001 0
0.
0,
1+
1*
1)
1(
0'
1/
#650000
0/
#655000
0"
02
01
1$
08
0#
0;
07
0:
b1000010 0
0+
0(
1/
#660000
0/
#665000
1"
1#
0$
0!
11
12
03
1%
0?
1<
19
06
b1000011 0
1.
0-
1,
1+
0*
0)
1(
1'
0&
1/
#670000
0/
#675000
0#
01
02
14
1=
0<
09
b1000100 0
0.
0,
0+
1*
1)
0(
0'
1/
#680000
0/
#685000
1#
1$
1:
17
b1000101 0
1,
1'
1/
#690000
0/
#695000
11
0#
1;
12
0$
18
1"
1!
0%
13
0=
1?
04
16
b1000110 0
1-
1&
1/
#700000
0/
#705000
0"
1>
1!
15
14
06
1=
0?
b1000111 0
1.
0*
0)
1/
#710000
0/
#715000
0!
1"
0>
01
1#
0;
02
1$
08
03
1%
05
b1001000 0
0.
0-
0,
1+
1*
1)
1(
0'
0&
1/
#720000
0/
#725000
1!
0"
1>
11
0#
1;
12
0$
18
13
0%
15
b1001001 0
1.
1-
1,
0+
0*
0)
0(
1'
1&
1/
#730000
0/
#735000
1$
08
1#
0;
07
19
0:
1<
b1001010 0
1+
1(
1/
#740000
0/
#745000
0$
0!
03
1"
0>
1%
05
0=
04
b1001011 0
0-
0&
1/
#750000
0/
#755000
1$
0#
13
01
02
0%
15
1=
0<
09
14
b1001100 0
1-
0,
0+
0(
0'
1&
1/
#760000
0/
#765000
0"
1!
05
04
16
0=
1?
b1001101 0
0.
1*
1)
1/
#770000
0/
#775000
1"
0!
1#
1%
03
1=
0?
1:
17
14
06
b1001110 0
0-
1,
1'
0&
1/
#780000
0/
#785000
1!
0"
1>
13
1$
12
1#
11
0%
15
07
19
0:
1<
b1001111 0
1.
1-
1+
0*
0)
1(
1&
1/
#790000
0/
#795000
1!
0"
1>
0$
18
12
0#
1;
11
17
09
1:
0<
b1010000 0
0+
0(
1/
#800000
0/
#805000
b1010001 0
0,
1+
1(
0'
1/
#810000
0/
#815000
b1010010 0
1/
#820000
0/
#825000
0!
1"
0>
02
01
1$
08
0#
0;
07
0:
b1010011 0
0+
0(
1/
#830000
0/
#835000
1#
1!
11
12
05
04
16
0=
1?
1<
19
b1010100 0
0.
1,
1+
1*
1)
1(
1'
1/
#840000
0/
#845000
0"
01
0!
02
03
1%
1:
0<
0?
17
09
06
b1010101 0
1.
0-
0,
0*
0)
0'
0&
1/
#850000
0/
#855000
1!
0#
13
0%
07
1?
0:
16
b1010110 0
0.
1-
0+
1*
1)
0(
1&
1/
#860000
0/
#865000
0!
1#
03
1%
17
0?
1:
06
b1010111 0
1.
0-
1+
0*
0)
1(
0&
1/
#870000
0/
#875000
1"
11
0$
12
0:
1<
07
19
b1011000 0
1,
1'
1/
#880000
0/
#885000
1$
1!
13
0"
1>
0%
15
1=
14
b1011001 0
1-
1&
1/
#890000
0/
#895000
0#
0>
01
02
05
04
16
0=
1?
0<
09
b1011010 0
0.
0,
0+
1*
1)
0(
0'
1/
#900000
0/
#905000
1"
0!
1#
1%
03
1=
0?
17
1:
14
06
b1011011 0
0-
1+
1(
0&
1/
#910000
0/
#915000
1!
0"
1>
11
0$
12
0:
1<
07
19
b1011100 0
1,
1'
1/
#920000
0/
#925000
1$
1"
0>
0%
13
0=
1?
04
16
b1011101 0
1-
1&
1/
#930000
0/
#935000
0!
01
02
1%
03
1=
0?
1:
0<
17
09
14
06
b1011110 0
0-
0,
0'
0&
1/
#940000
0/
#945000
1!
0"
1>
11
0$
12
0:
1<
07
19
b1011111 0
1,
1'
1/
#950000
0/
#955000
1!
18
0"
1>
13
0$
12
0#
1;
11
0%
15
17
09
1:
0<
b1100000 0
1.
1-
0+
0*
0)
0(
1&
1/
#960000
0/
#965000
0!
1"
0>
01
02
03
0#
0;
0$
08
1%
05
0:
07
b1100001 0
0.
0-
0,
1*
1)
0'
0&
1/
#970000
0/
#975000
0"
04
0=
b1100010 0
1.
0*
0)
1/
#980000
0/
#985000
1$
1#
17
1:
b1100011 0
1+
1(
1/
#990000
0/
#995000
1!
1>
11
0#
1;
12
0$
18
13
0"
0%
15
1=
14
b1100100 0
1-
1&
1/
